setup.py
src/tastytweets/README.rst
src/tastytweets/__init__.py
src/tastytweets/clearablequeue.py
src/tastytweets/client.py
src/tastytweets.egg-info/PKG-INFO
src/tastytweets.egg-info/SOURCES.txt
src/tastytweets.egg-info/dependency_links.txt
src/tastytweets.egg-info/entry_points.txt
src/tastytweets.egg-info/not-zip-safe
src/tastytweets.egg-info/requires.txt
src/tastytweets.egg-info/top_level.txt