Metadata-Version: 1.0
Name: tastytweets
Version: 0.2.1
Summary: delicious twitter mashup; finds twitter users posting links to urls you've tagged so you can start following them
Home-page: http://github.com/thruflo/tastytweets
Author: thruflo
Author-email: thruflo@googlemail.com
License: Public Domain
Platform: UNKNOWN
Classifier: Development Status :: 3 - Alpha
Classifier: Environment :: Web Environment
Classifier: Intended Audience :: Developers
Classifier: License :: Public Domain
Classifier: Programming Language :: Python
